c_syntax_validator/__init__.py
c_syntax_validator/__main__.py
c_syntax_validator/parser/CLexer.py
c_syntax_validator/parser/CListener.py
c_syntax_validator/parser/CParser.py
c_syntax_validator/parser/__init__.py
c_syntax_validator-0.2.0.dist-info/LICENSE.md
c_syntax_validator-0.2.0.dist-info/METADATA
c_syntax_validator-0.2.0.dist-info/WHEEL
c_syntax_validator-0.2.0.dist-info/top_level.txt
c_syntax_validator-0.2.0.dist-info/RECORD
