Metadata-Version: 2.1
Name: c-syntax-validator
Version: 0.2.0
Summary: Validates C syntax with an antlr parser
Home-page: https://github.com/Techcable/c-syntax-validator
Author: Techcable
Author-email: Techcable@techcable.net
License: MIT
Platform: UNKNOWN
Classifier: Development Status :: 3 - Alpha
Requires-Python: >=3.9
License-File: LICENSE.md
Provides-Extra: cli
Requires-Dist: click ; extra == 'cli'
